snakemake_jobmonitor/__init__.py
snakemake_jobmonitor/jobmonitor.py
snakemake_jobmonitor-0.1.2.dist-info/METADATA
snakemake_jobmonitor-0.1.2.dist-info/WHEEL
snakemake_jobmonitor-0.1.2.dist-info/licenses/LICENSE
snakemake_jobmonitor-0.1.2.dist-info/RECORD
