Metadata-Version: 2.4
Name: snakemake_jobmonitor
Version: 0.1.2
Summary: A new take on using Snakemake: pass around log-files instead of output-files
Project-URL: Homepage, https://github.com/rbakker/snakemake-jobmonitor
Project-URL: Issues, https://github.com/rbakker/snakemake-jobmonitor/issues
Author-email: Rembrandt Bakker <r.bakker@etz.nl>
License-Expression: MIT
License-File: LICENSE
Classifier: Operating System :: OS Independent
Classifier: Programming Language :: Python :: 3
